web3_collections/__init__.py
web3_collections/providers/__init__.py
web3_collections/providers/rpc.py
web3_collections-0.1.0.dist-info/LICENCE
web3_collections-0.1.0.dist-info/METADATA
web3_collections-0.1.0.dist-info/WHEEL
web3_collections-0.1.0.dist-info/top_level.txt
web3_collections-0.1.0.dist-info/RECORD
