Metadata-Version: 2.1
Name: web3-collections
Version: 0.1.0
Summary: Alternatives to some of the web3's classes
Home-page: https://github.com/MiKoronjoo/web3-collections
Author: MiKO
Author-email: mikoronjoo@gmail.com
Project-URL: Bug Tracker, https://github.com/MiKoronjoo/web3-collections/issues
Classifier: Programming Language :: Python :: 3
Classifier: License :: OSI Approved :: MIT License
Classifier: Operating System :: OS Independent
Requires-Python: <4.0.0,>=3.8.0
License-File: LICENCE
Requires-Dist: web3 <8.0.0,>=7.0.0
